scriptflow/__init__.py
scriptflow/cli.py
scriptflow/core.py
scriptflow/glob.py
scriptflow/runners.py
scriptflow/task.py
scriptflow-0.2.13.dist-info/METADATA
scriptflow-0.2.13.dist-info/WHEEL
scriptflow-0.2.13.dist-info/entry_points.txt
scriptflow-0.2.13.dist-info/RECORD
