Metadata-Version: 2.4
Name: scriptflow
Version: 0.2.13
Summary: Like a makefile but in python, a stripped-down system of Airflow or Luigi
Author: Thibaut Lamadon
Author-email: thibaut.lamadon@gmail.com
Requires-Python: >=3.8,<4.0
Classifier: Programming Language :: Python :: 3
Classifier: Programming Language :: Python :: 3.8
Classifier: Programming Language :: Python :: 3.9
Classifier: Programming Language :: Python :: 3.10
Classifier: Programming Language :: Python :: 3.11
Classifier: Programming Language :: Python :: 3.12
Classifier: Programming Language :: Python :: 3.13
Classifier: Programming Language :: Python :: 3.14
Provides-Extra: dask
Requires-Dist: asyncssh (>=2.9.0,<3.0.0)
Requires-Dist: click (>=8.0.3,<9.0.0)
Requires-Dist: omegaconf (>=2.1.1,<3.0.0)
Requires-Dist: requests (>=2.27.1,<3.0.0)
Requires-Dist: rich (>=14.0.0)
Requires-Dist: tinydb (>=4.7.0,<5.0.0)
Requires-Dist: toml (>=0.10.2,<0.11.0)
Project-URL: Repository, https://github.com/tlamadon/scriptflow
